SpringCloudRumenjiaochengCYuyanBianchengWangFix1/README.md
SpringCloudRumenjiaochengCYuyanBianchengWangFix1/__init__.py
SpringCloudRumenjiaochengCYuyanBianchengWangFix1/__main__.py
SpringCloudRumenjiaochengCYuyanBianchengWangFix1/file.epub
SpringCloudRumenjiaochengCYuyanBianchengWangFix1/index.html
SpringCloudRumenjiaochengCYuyanBianchengWangFix1/css/__init__.py
SpringCloudRumenjiaochengCYuyanBianchengWangFix1/css/annotations.css
SpringCloudRumenjiaochengCYuyanBianchengWangFix1/css/main.css
SpringCloudRumenjiaochengCYuyanBianchengWangFix1/css/normalize.css
SpringCloudRumenjiaochengCYuyanBianchengWangFix1/css/popup.css
SpringCloudRumenjiaochengCYuyanBianchengWangFix1/font/__init__.py
SpringCloudRumenjiaochengCYuyanBianchengWangFix1/font/fontello.eot
SpringCloudRumenjiaochengCYuyanBianchengWangFix1/font/fontello.svg
SpringCloudRumenjiaochengCYuyanBianchengWangFix1/font/fontello.ttf
SpringCloudRumenjiaochengCYuyanBianchengWangFix1/font/fontello.woff
SpringCloudRumenjiaochengCYuyanBianchengWangFix1/img/__init__.py
SpringCloudRumenjiaochengCYuyanBianchengWangFix1/img/annotator-glyph-sprite.png
SpringCloudRumenjiaochengCYuyanBianchengWangFix1/img/annotator-icon-sprite.png
SpringCloudRumenjiaochengCYuyanBianchengWangFix1/img/apple-touch-icon.png
SpringCloudRumenjiaochengCYuyanBianchengWangFix1/img/cancelfullscreen.png
SpringCloudRumenjiaochengCYuyanBianchengWangFix1/img/close.png
SpringCloudRumenjiaochengCYuyanBianchengWangFix1/img/fullscreen.png
SpringCloudRumenjiaochengCYuyanBianchengWangFix1/img/loader.gif
SpringCloudRumenjiaochengCYuyanBianchengWangFix1/img/menu-icon.png
SpringCloudRumenjiaochengCYuyanBianchengWangFix1/img/save.png
SpringCloudRumenjiaochengCYuyanBianchengWangFix1/img/saved.png
SpringCloudRumenjiaochengCYuyanBianchengWangFix1/img/settings-s.png
SpringCloudRumenjiaochengCYuyanBianchengWangFix1/img/settings.png
SpringCloudRumenjiaochengCYuyanBianchengWangFix1/img/star.png
SpringCloudRumenjiaochengCYuyanBianchengWangFix1/js/__init__.py
spring_cloud_rumenjiaocheng_c_yuyan_biancheng_wang_fix1-2025.3.24.1.dist-info/METADATA
spring_cloud_rumenjiaocheng_c_yuyan_biancheng_wang_fix1-2025.3.24.1.dist-info/WHEEL
spring_cloud_rumenjiaocheng_c_yuyan_biancheng_wang_fix1-2025.3.24.1.dist-info/entry_points.txt
spring_cloud_rumenjiaocheng_c_yuyan_biancheng_wang_fix1-2025.3.24.1.dist-info/top_level.txt
spring_cloud_rumenjiaocheng_c_yuyan_biancheng_wang_fix1-2025.3.24.1.dist-info/RECORD
